pychonet/AutomaticEntranceDoor.py
pychonet/BathroomDryer.py
pychonet/CeilingFan.py
pychonet/DistributionPanelMeter.py
pychonet/EchonetInstance.py
pychonet/ElectricBlind.py
pychonet/ElectricCurtain.py
pychonet/ElectricEnergyMeter.py
pychonet/ElectricGate.py
pychonet/ElectricHeater.py
pychonet/ElectricLock.py
pychonet/ElectricRainSlidingDoor.py
pychonet/ElectricShutter.py
pychonet/ElectricStorageHeater.py
pychonet/ElectricVehicleCharger.py
pychonet/ElectricWaterHeater.py
pychonet/ElectricWindow.py
pychonet/FanHeater.py
pychonet/FloorHeater.py
pychonet/FuelCell.py
pychonet/GasMeter.py
pychonet/GeneralLighting.py
pychonet/HomeAirCleaner.py
pychonet/HomeAirConditioner.py
pychonet/HomeSolarPower.py
pychonet/HotWaterGenerator.py
pychonet/HybridWaterHeater.py
pychonet/LightingSystem.py
pychonet/LowVoltageSmartElectricEnergyMeter.py
pychonet/MultipleInputPCS.py
pychonet/Refrigerator.py
pychonet/RiceCooker.py
pychonet/SingleFunctionLighting.py
pychonet/StorageBattery.py
pychonet/TemperatureSensor.py
pychonet/VisitorSensor.py
pychonet/WaterFlowMeter.py
pychonet/__init__.py
pychonet/echonetapiclient.py
pychonet/version.py
pychonet/lib/__init__.py
pychonet/lib/const.py
pychonet/lib/eojx.py
pychonet/lib/epc.py
pychonet/lib/epc_functions.py
pychonet/lib/functions.py
pychonet/lib/udpserver.py
pychonet-2.6.18.dist-info/LICENSE-GPL
pychonet-2.6.18.dist-info/LICENSE-MIT
pychonet-2.6.18.dist-info/METADATA
pychonet-2.6.18.dist-info/WHEEL
pychonet-2.6.18.dist-info/top_level.txt
pychonet-2.6.18.dist-info/RECORD
