Metadata-Version: 2.1
Name: pychonet
Version: 2.6.18
Summary: A library for interfacing via the ECHONETlite protocol.
Home-page: http://pypi.python.org/pypi/pychonet/
Author: Scott Phillips
Author-email: scotty.phillips@hotmail.com
License: LICENSE.txt
License-File: LICENSE-GPL
License-File: LICENSE-MIT
Requires-Dist: deprecated
